mxLogPy.cp311-win_amd64.pyd
mxLogPy/__init__.py
mxLogPy/mxLogPy.cp311-win_amd64.pyd
mxLogPy-0.1.9.dist-info/METADATA
mxLogPy-0.1.9.dist-info/WHEEL
mxLogPy-0.1.9.dist-info/top_level.txt
mxLogPy-0.1.9.dist-info/RECORD
