Metadata-Version: 2.1
Name: mxLogPy
Version: 0.1.9
Summary: High Performance and mutilThread & async Log Library by Cpp
Home-page: https://github.com/caomengxuan666/mxLog
Author: cmx
Author-email: 2507560089@qq.com
Classifier: Programming Language :: Python :: 3
Classifier: License :: OSI Approved :: MIT License
Classifier: Operating System :: OS Independent
Requires-Dist: pybind11
